AUTHORS.md
LICENSE
MANIFEST.in
README.md
setup.cfg
setup.py
mongobox/__init__.py
mongobox/mongobox.py
mongobox/nose2_plugin.py
mongobox/nose_plugin.py
mongobox/unittest.py
mongobox/utils.py
mongobox.egg-info/PKG-INFO
mongobox.egg-info/SOURCES.txt
mongobox.egg-info/dependency_links.txt
mongobox.egg-info/entry_points.txt
mongobox.egg-info/not-zip-safe
mongobox.egg-info/top_level.txt