Metadata-Version: 1.1
Name: mongobox
Version: 0.1.5
Summary: Run sandboxed Mongo DB instance from a python application.
Home-page: http://github.com/theorm/mongobox
Author: Roman Kalyakin <roman@kalyakin.com>
Author-email: roman@kalyakin.com
License: Copyright 2013 Roman Kalyakin
